baiduindex/__init__.py
baiduindex/index.py
baiduindex-0.0.1.dist-info/LICENSE
baiduindex-0.0.1.dist-info/METADATA
baiduindex-0.0.1.dist-info/WHEEL
baiduindex-0.0.1.dist-info/top_level.txt
baiduindex-0.0.1.dist-info/RECORD
