Metadata-Version: 2.1
Name: baiduindex
Version: 0.0.1
Summary: scary of baidu index
Home-page: https://github.com/zhyzhyzhy123/baiduindex
Author: hongyizhu
Author-email: 472739561@qq.com
License: UNKNOWN
Platform: UNKNOWN
Classifier: Programming Language :: Python :: 3
Classifier: License :: OSI Approved :: MIT License
Classifier: Operating System :: OS Independent
Requires-Python: >=3.6
License-File: LICENSE
